.gitignore
CHANGES.rst
CONTRIBUTORS.txt
COPYRIGHT.txt
LICENSE.txt
README.rst
setup.cfg
setup.py
tox.ini
doc/Makefile
doc/conf.py
doc/index.rst
doc/narrative.rst
doc/_static/placeholder.txt
doc/_templates/placeholder.txt
sweetpotatopie/__init__.py
sweetpotatopie/_compat.py
sweetpotatopie/interfaces.py
sweetpotatopie/parsers.py
sweetpotatopie.egg-info/PKG-INFO
sweetpotatopie.egg-info/SOURCES.txt
sweetpotatopie.egg-info/dependency_links.txt
sweetpotatopie.egg-info/not-zip-safe
sweetpotatopie.egg-info/requires.txt
sweetpotatopie.egg-info/top_level.txt
sweetpotatopie/tests/__init__.py
sweetpotatopie/tests/test_parsers.py